{
    "java_ram_min": "2G",
    "java_ram_max": "4G",
    "backup_time": "03:00",
    "backup_keep_days": 7,
    "restart_time": "04:00",
    "timezone": "Europe/Ljubljana",
    "permissions": {
        "Owner": [
            "cmd",
            "sync",
            "bot_restart",
            "start",
            "stop",
            "restart",
            "control",
            "backup",
            "backup_now",
            "backup_list",
            "backup_download",
            "logs",
            "whitelist_add",
            "set_spawn",
            "status",
            "players",
            "seed",
            "version",
            "info",
            "mods",
            "stats",
            "help",
            "balance",
            "pay",
            "economy_set",
            "event_create",
            "event_list",
            "event_delete",
            "motd",
            "trigger_add",
            "trigger_list",
            "trigger_remove",
            "ai"
        ],
        "Admin": [
            "start",
            "stop",
            "restart",
            "control",
            "backup",
            "backup_now",
            "backup_list",
            "backup_download",
            "logs",
            "whitelist_add",
            "set_spawn",
            "status",
            "players",
            "seed",
            "version",
            "info",
            "mods",
            "stats",
            "help",
            "balance",
            "pay",
            "event_create",
            "event_list",
            "event_delete",
            "motd",
            "trigger_add",
            "trigger_list",
            "trigger_remove"
        ],
        "Player": [
            "status",
            "players",
            "seed",
            "version",
            "info",
            "mods",
            "stats",
            "help",
            "balance",
            "pay",
            "backup",
            "backup_list",
            "event_list"
        ],
        "@everyone": [
            "status",
            "players",
            "seed",
            "version",
            "info",
            "mods",
            "help"
        ]
    }
}